py_steam_web_api/__init__.py
py_steam_web_api/api.py
py_steam_web_api/common.py
py_steam_web_api/model.py
py_steam_web_api/request.py
py_steam_web_api/tools.py
py_steam_web_api-0.2.dist-info/LICENSE
py_steam_web_api-0.2.dist-info/METADATA
py_steam_web_api-0.2.dist-info/WHEEL
py_steam_web_api-0.2.dist-info/top_level.txt
py_steam_web_api-0.2.dist-info/RECORD
