Metadata-Version: 2.1
Name: py-steam-web-api
Version: 0.2
Summary: Python Client wrapper for Steam Web API
Home-page: https://github.com/sylas00/py-steam-web-api
Author: sylas00
Author-email: xyjy5247@gmail.com
Keywords: steam,steam api,steam community,steam web api
Requires-Python: >=3.8
License-File: LICENSE
Requires-Dist: requests >=2.31.0
